Metadata-Version: 1.1
Name: wordbook
Version: 1.0.0
Summary: Python client for DICT Servers
Home-page: http://github.com/tomplus/wordbook
Author: Tomasz Prus
Author-email: tomasz.prus@gmail.com
License: MIT
Keywords: DICT,dictionary
Platform: UNKNOWN
Classifier: Development Status :: 4 - Beta
Classifier: Environment :: Console
Classifier: Intended Audience :: Developers
Classifier: License :: OSI Approved :: MIT License
Classifier: Operating System :: OS Independent
Classifier: Programming Language :: Python
Classifier: Programming Language :: Python :: 3
Classifier: Programming Language :: Python :: 3.5
Classifier: Programming Language :: Python :: 3.6
